[
  {
    "id": 0,
    "statement": "PFC top-down signals modulate thalamus's attentional filtering through corticothalamic connections."
  },
  {
    "id": 1,
    "statement": "Cortical top-down feedback refines thalamic processing through attentional modulation."
  },
  {
    "id": 2,
    "statement": "Thalamus refines sensory information through dynamic neural processing."
  },
  {
    "id": 3,
    "statement": "Thalamus integrates sensory and spatial information for cognition."
  },
  {
    "id": 4,
    "statement": "Cognitive empathy involves perspective-taking, emotional understanding, and regulation."
  },
  {
    "id": 5,
    "statement": "Cognitive empathy involves perspective-taking, emotional understanding, and regulation."
  },
  {
    "id": 6,
    "statement": "Attentional filtering involves dynamic coordination of multiple brain regions."
  },
  {
    "id": 7,
    "statement": "Brain processes sensory information in hierarchical layers through neural networks."
  },
  {
    "id": 8,
    "statement": "Empathy involves cognitive understanding, emotional regulation, and compassion."
  },
  {
    "id": 9,
    "statement": "Thalamus's filtering role debated due to complexity, multiple roles."
  },
  {
    "id": 10,
    "statement": "PFC and Thalamus communicate bidirectionally through Glutamate and AMPA receptors."
  },
  {
    "id": 11,
    "statement": "Thalamus's attentional filtering role debated due to complexity."
  },
  {
    "id": 12,
    "statement": "Empathy's neural basis unclear, requires further research."
  },
  {
    "id": 13,
    "statement": "Thalamus refines sensory info through dynamic neural filtering."
  },
  {
    "id": 14,
    "statement": "The thalamus integrates diverse sensory and spatial information for cognition."
  },
  {
    "id": 15,
    "statement": "Synaptic plasticity refines sensory info through pattern separation and strengthening."
  },
  {
    "id": 16,
    "statement": "In scientific writing, technical language should be precise, not embellished."
  },
  {
    "id": 17,
    "statement": "Thalamus's filtering role complex, debated, context-dependent, dynamic, and multifaceted."
  },
  {
    "id": 18,
    "statement": "Cognitive empathy linked to emotional regulation through shared ACC-insula networks."
  },
  {
    "id": 19,
    "statement": "Cognitive empathy involves interplay of emotional regulation and compassion"
  },
  {
    "id": 20,
    "statement": "Thalamus integrates diverse sensory and spatial information dynamically."
  },
  {
    "id": 21,
    "statement": "Thalamus's exact role in sensory processing remains an ongoing focus."
  },
  {
    "id": 22,
    "statement": "Thalamus dynamically filters sensory information through neural interactions."
  },
  {
    "id": 23,
    "statement": "Thalamus refines sensory information through dynamic neural processing."
  },
  {
    "id": 24,
    "statement": "Cognitive empathy linked to emotional regulation through ACC-insula networks."
  },
  {
    "id": 25,
    "statement": "Brain processes sensory information hierarchically through neural connections."
  },
  {
    "id": 26,
    "statement": "Thalamus's filtering role debated among neuroscientists due to complexity."
  },
  {
    "id": 27,
    "statement": "Cortical attention modulates thalamic filtering for sensory refinement."
  },
  {
    "id": 28,
    "statement": "Empathetic listening involves validating emotions without judgment"
  },
  {
    "id": 29,
    "statement": "Glutamate excites thalamic neurons through AMPA and NMDA receptors."
  },
  {
    "id": 30,
    "statement": "Thalamus's filtering role debated due to complexity and multifaceted function."
  },
  {
    "id": 31,
    "statement": "Synaptic Plasticity Refines Sensory Info Through Neural Connection Reorganization."
  },
  {
    "id": 32,
    "statement": "Hierarchical processing of sensory information subject to ongoing debate among neuroscientists."
  },
  {
    "id": 33,
    "statement": "Thalamus refines sensory information through dynamic neural interactions ultimately."
  },
  {
    "id": 34,
    "statement": "Thalamus's filtering role complex due to multifaceted neural interactions."
  },
  {
    "id": 35,
    "statement": "Thalamus's filtering function involves complex neural interactions mechanisms."
  },
  {
    "id": 36,
    "statement": "Cognitive empathy linked to emotional regulation through ACC-insula networks."
  },
  {
    "id": 37,
    "statement": "Glutamate mediates excitation of thalamic neurons through AMPA and NMDA receptors"
  },
  {
    "id": 38,
    "statement": "PFC influences thalamus's attentional filtering through corticothalamic connections."
  },
  {
    "id": 39,
    "statement": "Cognitive understanding, emotional regulation, and compassion form empathy's foundation components."
  },
  {
    "id": 40,
    "statement": "Attentional filtering involves complex neural network coordination across regions."
  },
  {
    "id": 41,
    "statement": "Synaptic plasticity refines sensory processing through experience-dependent reorganization dynamically."
  },
  {
    "id": 42,
    "statement": "Cortical attentional modulation refines sensory info through thalamic filtering."
  },
  {
    "id": 43,
    "statement": "Glutamate excites thalamic neurons through AMPA and NMDA receptors."
  },
  {
    "id": 44,
    "statement": "Thalamus dynamically filters sensory information through neural interactions."
  },
  {
    "id": 45,
    "statement": "Thalamus's filtering role debated among neuroscientists due to complexity."
  },
  {
    "id": 46,
    "statement": "Cognitive empathy involves regulating one's own emotions for better understanding."
  },
  {
    "id": 47,
    "statement": "Glutamate mediates excitatory communication between PFC and thalamus"
  },
  {
    "id": 48,
    "statement": "Cognitive empathy linked to emotional regulation through ACC and insula"
  },
  {
    "id": 49,
    "statement": "Glutamate enables bidirectional PFC-thalamus communication through AMPA receptors."
  },
  {
    "id": 50,
    "statement": "Thalamus filters sensory info through dynamic neural network interactions."
  },
  {
    "id": 51,
    "statement": "Empathetic listening creates connection through validation and non-judgmental space."
  },
  {
    "id": 52,
    "statement": "Empathetic listening involves acknowledging and acceptance of emotions."
  },
  {
    "id": 53,
    "statement": "AMPA/NMDA signaling enables bidirectional neural communication."
  },
  {
    "id": 54,
    "statement": "Cortical attentional modulation enhances selective sensory processing in thalamus."
  },
  {
    "id": 55,
    "statement": "Brain's hierarchical processing of sensory information debated among neuroscientists."
  },
  {
    "id": 56,
    "statement": "Corticothalamic pathways enable bidirectional neural communication dynamically."
  },
  {
    "id": 57,
    "statement": "Thalamus's filtering role debated among neuroscientists due to complexity."
  },
  {
    "id": 58,
    "statement": "Cognitive empathy linked to emotional regulation in shared neural networks."
  },
  {
    "id": 59,
    "statement": "The Thalamus dynamically filters sensory information through neural interactions."
  },
  {
    "id": 60,
    "statement": "Thalamus filters sensory info through complex neural interactions, mechanisms."
  },
  {
    "id": 61,
    "statement": "Cortical attention modulates thalamus refinement through selective filtering."
  },
  {
    "id": 62,
    "statement": "Thalamus refines sensory info through neural oscillations, synaptic plasticity, and corticothalamic interactions."
  },
  {
    "id": 63,
    "statement": "Thalamus processes sensory info through corticothalamic, thalamocortical connections dynamically."
  },
  {
    "id": 64,
    "statement": "Brain's hierarchical processing is debated, complex, and multifaceted between innateness and learning"
  },
  {
    "id": 65,
    "statement": "Thalamus integrates sensory information through synchronized neural oscillations."
  },
  {
    "id": 66,
    "statement": "Thalamus's complex role in sensory processing is debated among neuroscientists."
  },
  {
    "id": 67,
    "statement": "Corticothalamic projection enables top-down control of thalamus activity."
  },
  {
    "id": 68,
    "statement": "Brain's neural processing occurs in hierarchical layers converging complex information."
  },
  {
    "id": 69,
    "statement": "Glutamate is an excitatory neurotransmitter for thalamic neurons."
  },
  {
    "id": 70,
    "statement": "Thalamus integrates sensory information through synchronization and spatial mapping."
  },
  {
    "id": 71,
    "statement": "Brain's attentional filtering involves complex neural network coordination."
  },
  {
    "id": 72,
    "statement": "Thalamus's filtering role debated among neuroscientists due to complexity."
  },
  {
    "id": 73,
    "statement": "Thalamus's filtering role debated among neuroscientists due to complexity."
  },
  {
    "id": 74,
    "statement": "Corticothalamic pathways facilitate bidirectional neural communication dynamically."
  },
  {
    "id": 75,
    "statement": "Cognitive empathy linked to emotional regulation through shared neural networks."
  },
  {
    "id": 76,
    "statement": "Brain's neural processes integrate sensory information in hierarchical manner"
  },
  {
    "id": 77,
    "statement": "Synaptic plasticity refines sensory info through neural connection reorganization."
  },
  {
    "id": 78,
    "statement": "Cognitive empathy linked to emotional regulation through shared ACC-insula networks."
  },
  {
    "id": 79,
    "statement": "Cortical attention modulates thalamus through top-down corticothalamic signals."
  },
  {
    "id": 80,
    "statement": "Synaptic plasticity refines sensory information through neural connection reorganization."
  },
  {
    "id": 81,
    "statement": "Technical language in science conveys complex ideas accurately."
  },
  {
    "id": 82,
    "statement": "Emotional regulation in empathy involves brain regions' coordinated activity."
  },
  {
    "id": 83,
    "statement": "Cortical attentional modulation refines sensory info through corticothalamic pathways."
  },
  {
    "id": 84,
    "statement": "PFC modulation highlights attention's complex neural interactions."
  },
  {
    "id": 85,
    "statement": "Cortical attentional modulation refines sensory info through corticothalamic pathways."
  },
  {
    "id": 86,
    "statement": "Perspective-taking involves simulating and inferring others' thoughts and feelings."
  },
  {
    "id": 87,
    "statement": "Thalamus dynamically filters sensory info through neural interactions."
  },
  {
    "id": 88,
    "statement": "Corticothalamic pathways enable bidirectional neural communication dynamically."
  },
  {
    "id": 89,
    "statement": "Cognitive empathy involves shared neural networks for emotional regulation."
  },
  {
    "id": 90,
    "statement": "The thalamus refines sensory information through neural oscillations."
  },
  {
    "id": 91,
    "statement": "Thalamus refines sensory info through complex neural interactions."
  },
  {
    "id": 92,
    "statement": "Thalamus refines sensory info through complex neural interactions."
  },
  {
    "id": 93,
    "statement": "Synaptic plasticity induced by experiences, LTP and LTD processes."
  },
  {
    "id": 94,
    "statement": "Thalamus refines sensory info through neural interactions' types."
  },
  {
    "id": 95,
    "statement": "Thalamus's neural interactions refine sensory information dynamically."
  },
  {
    "id": 96,
    "statement": "Glutamate mediates bidirectional PFC-thalamus communication through AMPA/NMDA signaling"
  },
  {
    "id": 97,
    "statement": "Thalamus refines sensory info through cortical attentional modulation."
  },
  {
    "id": 98,
    "statement": "Thalamus acts as a dynamic relay station filtering sensory information."
  },
  {
    "id": 99,
    "statement": "Thalamus adaptively reorganizes neural connections for sensory processing."
  },
  {
    "id": 100,
    "statement": "Thalamus's filtering role involves complex neural interactions dynamically."
  },
  {
    "id": 101,
    "statement": "Glutamate mediates excitatory PFC-thalamus communication through AMPActors."
  },
  {
    "id": 102,
    "statement": "Cognitive understanding, emotional regulation, and compassion form empathy's foundation."
  },
  {
    "id": 103,
    "statement": "The thalamus filters sensory info through dynamic neural processing."
  },
  {
    "id": 104,
    "statement": "Cortical-thalamic pathways enable dynamic bidirectional neural communication."
  },
  {
    "id": 105,
    "statement": "PFC top-down signals modulate thalamic sensory information processing."
  },
  {
    "id": 106,
    "statement": "Thalamus refines sensory info through corticothalamic feedback loops."
  },
  {
    "id": 107,
    "statement": "Thalamus dynamically filters sensory information through neural interactions."
  },
  {
    "id": 108,
    "statement": "Glutamate excites neurons through AMPA and NMDA receptors"
  },
  {
    "id": 109,
    "statement": "Cognitive empathy linked to emotional regulation through interaction between ACC and insula"
  },
  {
    "id": 110,
    "statement": "Thalamus: multidimensional structure with complex neural interactions."
  },
  {
    "id": 111,
    "statement": "Synaptic plasticity enables thalamus to adaptively reorganize neural connections."
  },
  {
    "id": 112,
    "statement": "The thalamus's dual function sparks debate among neuroscientists."
  },
  {
    "id": 113,
    "statement": "Empathy arises from complex interplay of cognitive, emotional, and compassionate understanding."
  },
  {
    "id": 114,
    "statement": "Thalamus's filtering role debated among neuroscientists due to multifaceted factors."
  },
  {
    "id": 115,
    "statement": "Empathy arises from complex interplay of cognitive understanding, emotional regulation, and compassion."
  },
  {
    "id": 116,
    "statement": "Thalamus refines sensory info through oscillations, synchrony, and filtering."
  },
  {
    "id": 117,
    "statement": "Thalamus's filtering role complex, multifaceted, and context-dependent."
  },
  {
    "id": 118,
    "statement": "Glutamate enables bidirectional PFC-thalamus communication through AMPA and NMDA receptors."
  },
  {
    "id": 119,
    "statement": "Glutamate excites thalamic neurons through AMPA and NMDA receptors'"
  },
  {
    "id": 120,
    "statement": "Synaptic plasticity refines sensory info through pattern separation and strengthening."
  },
  {
    "id": 121,
    "statement": "Corticothalamic pathways enable bidirectional dynamic neural communication."
  },
  {
    "id": 122,
    "statement": "ACC and insula enable emotional processing for empathy."
  },
  {
    "id": 123,
    "statement": "Synaptic plasticity refines sensory info through pattern separation and strengthening."
  },
  {
    "id": 124,
    "statement": "Thalamus refines sensory info through adaptive neural processing mechanisms."
  },
  {
    "id": 125,
    "statement": "Glutamate enables bidirectional PFC-thalamus communication through AMPA receptors."
  },
  {
    "id": 126,
    "statement": "The thalamus plays multiple roles in brain processing, filtering and regulation"
  },
  {
    "id": 127,
    "statement": "Thalamus refines sensory info through corticothalamic, thalamocortical connections."
  },
  {
    "id": 128,
    "statement": "Experiences induce synaptic plasticity through LTP and LTD processes"
  },
  {
    "id": 129,
    "statement": "PFC and Thalamus communicate bidirectionally through glutamate and AMPA receptors"
  },
  {
    "id": 130,
    "statement": "Glutamate excites thalamic neurons through AMPA and NMDA receptors."
  },
  {
    "id": 131,
    "statement": "Synaptic plasticity enables adaptive reorganization of thalamus's neural connections."
  },
  {
    "id": 132,
    "statement": "Glutamate enables bidirectional PFC-thalamus communication through AMPA receptors' synapse"
  },
  {
    "id": 133,
    "statement": "ACC and Insula jointly process emotional stimuli for empathy."
  },
  {
    "id": 134,
    "statement": "Thalamus adapts neural connections through synaptic plasticity and reorganization."
  },
  {
    "id": 135,
    "statement": "Thalamus dynamically integrates diverse sensory information in real-time accurately."
  },
  {
    "id": 136,
    "statement": "Glutamate excites thalamic neurons through AMPA and NMDA receptors."
  },
  {
    "id": 137,
    "statement": "Thalamus acts as dynamic relay station filtering sensory information."
  },
  {
    "id": 138,
    "statement": "Compassion enhances emotional regulation in cognitive empathy."
  },
  {
    "id": 139,
    "statement": "Thalamus integrates sensory information for higher-level cognitive processes."
  },
  {
    "id": 140,
    "statement": "Cortical attention modulation refines thalamic sensory processing via corticothalamic connections."
  },
  {
    "id": 141,
    "statement": "Thalamus selectively amplifies relevant sensory information under attentional demands."
  },
  {
    "id": 142,
    "statement": "Glutamate excites thalamic neurons through AMPA and NMDA receptors"
  },
  {
    "id": 143,
    "statement": "Corticothalamic pathways enable dynamic bidirectional neural communication."
  },
  {
    "id": 144,
    "statement": "Thalamus processes sensory info through hierarchical neural networks."
  },
  {
    "id": 145,
    "statement": "Thalamus filters sensory information through complex neural interactions."
  },
  {
    "id": 146,
    "statement": "Synaptic plasticity refines sensory processing through experience-dependent reorganization dynamically."
  },
  {
    "id": 147,
    "statement": "Thalamus's filtering role complex, multifaceted, context-dependent and debated"
  },
  {
    "id": 148,
    "statement": "Thalamus refines sensory info through cortical attentional modulation."
  },
  {
    "id": 149,
    "statement": "Cognitive empathy involves regulating one's emotions for better understanding."
  },
  {
    "id": 150,
    "statement": "Thalamus's filtering role debated due to hierarchical organization complexity."
  },
  {
    "id": 151,
    "statement": "Thalamus plays multiple roles in brain processing and regulation."
  },
  {
    "id": 152,
    "statement": "PFC top-down signals modulate thalamic sensory information processing through attentional filtering."
  },
  {
    "id": 153,
    "statement": "Thalamus's attentional filtering role complex and multifaceted."
  },
  {
    "id": 154,
    "statement": "Thalamus processes sensory info through complex neural interactions and mechanisms."
  },
  {
    "id": 155,
    "statement": "Glutamate excites thalamic neurons through multiple receptor subtypes."
  },
  {
    "id": 156,
    "statement": "Thalamus filters sensory info adaptively, influenced by context."
  },
  {
    "id": 157,
    "statement": "Empathy arises from intricate cognitive, emotional, and social processes."
  },
  {
    "id": 158,
    "statement": "Thalamus's filtering role complex due to multiple neural interactions."
  },
  {
    "id": 159,
    "statement": "Cortical attentional modulation dynamically filters sensory information."
  },
  {
    "id": 160,
    "statement": "Corticothalamic pathways enable bidirectional dynamic neural processing."
  },
  {
    "id": 161,
    "statement": "Glutamate enables bidirectional PFC-thalamus communication through AMPA/NMDA receptors."
  },
  {
    "id": 162,
    "statement": "Thalamus refines sensory info through complex neural mechanisms."
  },
  {
    "id": 163,
    "statement": "Glutamate enables bidirectional PFC-thalamus communication through AMPA receptors."
  },
  {
    "id": 164,
    "statement": "Hierarchical sensory processing debated among neuroscientists."
  },
  {
    "id": 165,
    "statement": "Thalamus's filtering role nuanced, context-dependent, and debated partially."
  },
  {
    "id": 166,
    "statement": "Attentional filtering involves dynamic coordination of brain regions."
  },
  {
    "id": 167,
    "statement": "Thalamus's filtering role debated among neuroscientists due to complexity."
  },
  {
    "id": 168,
    "statement": "Thalamus dynamically filters sensory info through neural processing mechanisms"
  },
  {
    "id": 169,
    "statement": "Synaptic plasticity refines sensory info through LTP and LTD processes."
  },
  {
    "id": 170,
    "statement": "Neural oscillations facilitate sensory information processing in thalamus"
  },
  {
    "id": 171,
    "statement": "Empathetic listening involves understanding, active listening, and validation."
  },
  {
    "id": 172,
    "statement": "Empathetic listening creates connection through validation and acceptance."
  },
  {
    "id": 173,
    "statement": "Empathetic listening involves validating emotions without judgment or agreement."
  },
  {
    "id": 174,
    "statement": "Cortical top-down feedback filters thalamus' sensory information refinement."
  },
  {
    "id": 175,
    "statement": "Thalamus refines sensory information through neural interactions, filtering."
  },
  {
    "id": 176,
    "statement": "Brain processes sensory information in hierarchical, step-by-step manner via neural connections."
  },
  {
    "id": 177,
    "statement": "Thalamus refines sensory information through synchronization, filtering, modulation, and feedback."
  },
  {
    "id": 178,
    "statement": "The thalamus refines sensory information through dynamic neural processing mechanisms."
  },
  {
    "id": 179,
    "statement": "Thalamus refines sensory information through complex neural interactions dynamically."
  },
  {
    "id": 180,
    "statement": "Thalamus engages in continuous sensory information refinement dynamically."
  },
  {
    "id": 181,
    "statement": "Thalamus plays multiple roles in brain processing, filtering and regulation."
  },
  {
    "id": 182,
    "statement": "Thalamus integrates diverse sensory information for cognition and perception."
  },
  {
    "id": 183,
    "statement": "Corticothalamic projection enables top-down modulation of thalamus activity."
  },
  {
    "id": 184,
    "statement": "Brain's attentional filtering involves dynamic neural network coordination."
  },
  {
    "id": 185,
    "statement": "Thalamus refines sensory info through neural oscillations, plasticity, and interactions."
  },
  {
    "id": 186,
    "statement": "Thalamus involved in sensory processing, attention, and cognition."
  },
  {
    "id": 187,
    "statement": "Empathy involves complex neural mechanisms and unclear neural pathways."
  },
  {
    "id": 188,
    "statement": "Empathy arises from cognitive, emotional, and compassionate understanding interactions."
  },
  {
    "id": 189,
    "statement": "Brain processes sensory information hierarchically through neural connections."
  },
  {
    "id": 190,
    "statement": "Glutamate excites neurons through AMPA, NMDA receptor binding."
  },
  {
    "id": 191,
    "statement": "Thalamus refines sensory information through neural oscillations and plasticity."
  },
  {
    "id": 192,
    "statement": "Cognitive empathy linked to emotional regulation through shared neural networks."
  },
  {
    "id": 193,
    "statement": "Synaptic plasticity refines sensory info through pattern separation and strengthening."
  },
  {
    "id": 194,
    "statement": "Cortico-thalamic connections enable dynamic sensory information processing."
  },
  {
    "id": 195,
    "statement": "Neural coordination across regions filters sensory information efficiently."
  },
  {
    "id": 196,
    "statement": "Cognitive empathy involves iterative perspective-taking, emotional understanding, regulation."
  },
  {
    "id": 197,
    "statement": "Thalamus dynamically filters sensory info through neural interactions."
  },
  {
    "id": 198,
    "statement": "Thalamus filters sensory info through neural interactions and oscillations."
  },
  {
    "id": 199,
    "statement": "Corticothalamic pathways enable bidirectional neural communication dynamically."
  }
]