[
  {
    "id": 0,
    "statement": "It is never morally acceptable to lie because honesty is the foundation of trust."
  },
  {
    "id": 1,
    "statement": "Thalamus filters sensory info through neural oscillations and gating mechanisms."
  },
  {
    "id": 2,
    "statement": "Consistency, reliability, and dependability build trust through predictability and stability."
  },
  {
    "id": 3,
    "statement": "Biological and cultural factors interact reciprocally in moral development."
  },
  {
    "id": 4,
    "statement": "Hierarchical processing enables amygdala's rapid emotion pattern recognition."
  },
  {
    "id": 5,
    "statement": "Amygdala's emotional responses refined through synaptic plasticity refinement."
  },
  {
    "id": 6,
    "statement": "Cultural norms influence emotional expressions and trust-building behaviors universally."
  },
  {
    "id": 7,
    "statement": "Biological and cultural factors interact reciprocally influencing moral development."
  },
  {
    "id": 8,
    "statement": "Amygdala's hierarchical processing rapidly detects emotional patterns through integration."
  },
  {
    "id": 9,
    "statement": "GABA's inhibitory action reduces neuron excitability through hyperpolarization."
  },
  {
    "id": 10,
    "statement": "Hierarchical amygdala processing rapidly detects emotional patterns via integration."
  },
  {
    "id": 11,
    "statement": "Honesty is a foundation of trust, established through reliability."
  },
  {
    "id": 12,
    "statement": "Consistency, reliability, dependability drive trust through predictability and stability."
  },
  {
    "id": 13,
    "statement": "Consistency, reliability, dependability, predictability, and stability build trust through reliability."
  },
  {
    "id": 14,
    "statement": "GABA reduces neuronal excitability by increasing chloride ion influx"
  },
  {
    "id": 15,
    "statement": "Consistency, predictability, and stability build trust through emotional regulation."
  },
  {
    "id": 16,
    "statement": "Amygdala refines emotional responses through synaptic plasticity adaptation."
  },
  {
    "id": 17,
    "statement": "Thalamus neural oscillations modulate sensory information gating."
  },
  {
    "id": 18,
    "statement": "Trust emerges when emotional stability fosters consistent predictable behavior."
  },
  {
    "id": 19,
    "statement": "Amygdala refines emotional responses through synaptic plasticity adaptation."
  },
  {
    "id": 20,
    "statement": "Emotional stability fosters consistency, predictability in building trust."
  },
  {
    "id": 21,
    "statement": "Emotional stability fosters consistent and predictable behavior through self-regulation."
  },
  {
    "id": 22,
    "statement": "Building trust involves cumulative effect of consistency, reliability, and predictability."
  },
  {
    "id": 23,
    "statement": "Moral development emerges from dynamic biological-cultural interactions."
  },
  {
    "id": 24,
    "statement": "Moral development occurs through reciprocal biological-cultural interactions."
  },
  {
    "id": 25,
    "statement": "Cognitive factors, particularly pattern recognition, build trust through interpretation."
  },
  {
    "id": 26,
    "statement": "Emotional stability fosters behavior regulation for trust building."
  },
  {
    "id": 27,
    "statement": "GABA calms neurons by opening chloride channels."
  },
  {
    "id": 28,
    "statement": "Moral development results from biology-culture reciprocal interplay influencing each other."
  },
  {
    "id": 29,
    "statement": "Familiarity fosters trust through cognitive and emotional pattern recognition"
  },
  {
    "id": 30,
    "statement": "Consistency, predictability, and transparency are foundation of trust"
  },
  {
    "id": 31,
    "statement": "GABA's inhibitory action hyperpolarizes neurons, reducing excitability."
  },
  {
    "id": 32,
    "statement": "Hierarchical amygdala processing rapidly detects emotional patterns via integration."
  },
  {
    "id": 33,
    "statement": "The amygdala integrates sensory and motor information for emotional recognition."
  },
  {
    "id": 34,
    "statement": "GABA reduces neuronal excitability through Cl- and K+ ion channels."
  },
  {
    "id": 35,
    "statement": "Transparency builds trust through establishing clear expectations."
  },
  {
    "id": 36,
    "statement": "Cultural socialization influences essential emotional responses and regulation"
  },
  {
    "id": 37,
    "statement": "The amygdala rapidly analyzes sensory information through parallel processing."
  },
  {
    "id": 38,
    "statement": "Amygdala's hierarchical processing integrates sensory and emotional information rapidly."
  },
  {
    "id": 39,
    "statement": "The amygdala rapidly integrates sensory and emotional information hierarchically."
  },
  {
    "id": 40,
    "statement": "The amygdala refines emotional responses through synaptic plasticity adaptation."
  },
  {
    "id": 41,
    "statement": "Cultural norms influence emotional expressions and trust-building behaviors complexly."
  },
  {
    "id": 42,
    "statement": "Transparency alone is not enough to build trust."
  },
  {
    "id": 43,
    "statement": "Transparency builds trust through clear expectations established."
  },
  {
    "id": 44,
    "statement": "Thalamus modulates sensory processing based on attentional state."
  },
  {
    "id": 45,
    "statement": "Amygdala refines emotional responses through synaptic plasticity updates"
  },
  {
    "id": 46,
    "statement": "Emotional stability influences behavior through complex bidirectional relationships."
  },
  {
    "id": 47,
    "statement": "Biological factors such as brain, genes, hormones, emotions influence moral development"
  },
  {
    "id": 48,
    "statement": "Emotional stability fosters predictable consistent behavioral patterns through regulation."
  },
  {
    "id": 49,
    "statement": "Amygdala recognizes patterns in sensory info through hierarchical processing."
  },
  {
    "id": 50,
    "statement": "Amygdala's pattern recognition is shaped by internal and external factors."
  },
  {
    "id": 51,
    "statement": "Emotional stability fosters consistent predictable behavior through self-regulation."
  },
  {
    "id": 52,
    "statement": "Amygdala's synaptic plasticity refines emotional responses through connection modification."
  },
  {
    "id": 53,
    "statement": "GABA's inhibitory action hyperpolarizes neurons, reduces excitability"
  },
  {
    "id": 54,
    "statement": "Amygdala recognizes patterns in sensory info through hierarchical processing."
  },
  {
    "id": 55,
    "statement": "Thalamus modulates sensory processing based on attentional state dynamically."
  },
  {
    "id": 56,
    "statement": "The amygdala rapidly processes sensory information through hierarchical processing."
  },
  {
    "id": 57,
    "statement": "Biological and cultural factors interact reciprocally shaping moral development."
  },
  {
    "id": 58,
    "statement": "Amygdala's emotional responses refined through modifiable connections"
  },
  {
    "id": 59,
    "statement": "Emotional stability fosters consistency, predictability, and transparency in trust."
  },
  {
    "id": 60,
    "statement": "Reliability builds trust by establishing confidence in consistent performance."
  },
  {
    "id": 61,
    "statement": "Emotional regulation, self-awareness, and resilience are interdependent components"
  },
  {
    "id": 62,
    "statement": "Amygdala's pattern recognition shaped by genetics, experience, and culture."
  },
  {
    "id": 63,
    "statement": "Moral development arises from interplay between biology and culture."
  },
  {
    "id": 64,
    "statement": "The amygdala integrates sensory, memory, and attention hierarchically in processing, facilitating rapid emotional detection."
  },
  {
    "id": 65,
    "statement": "Honesty is a foundation of trust, but not exclusively"
  },
  {
    "id": 66,
    "statement": "Cultural norms shape emotional expressions uniquely through internalization."
  },
  {
    "id": 67,
    "statement": "Emotional salience influences attention and neural oscillations interactively."
  },
  {
    "id": 68,
    "statement": "The amygdala processes threat patterns hierarchically from sensory inputs."
  },
  {
    "id": 69,
    "statement": "Emotional regulation relies on self-awareness for effective functioning"
  },
  {
    "id": 70,
    "statement": "Dynastic brain oscillations modulate amygdala activity in emotional processing."
  },
  {
    "id": 71,
    "statement": "Consistency, predictability, and stability create trust through emotional regulation."
  },
  {
    "id": 72,
    "statement": "Cultural norms significantly influence emotional expressions universally."
  },
  {
    "id": 73,
    "statement": "Emotional stability is dynamic process influenced by complex relationships."
  },
  {
    "id": 74,
    "statement": "Reliability combines dependability and consistency in performance over time."
  },
  {
    "id": 75,
    "statement": "Consistency, reliability, and predictability build trust interactively."
  },
  {
    "id": 76,
    "statement": "Dependability and consistency combine to form trustworthiness."
  },
  {
    "id": 77,
    "statement": "Emotional stability fosters trust through consistent predictable behavior."
  },
  {
    "id": 78,
    "statement": "Gamma waves integrate brain regions for emotional processing coherence."
  },
  {
    "id": 79,
    "statement": "Emotional stability is dynamic interplay of multiple biological and cultural factors"
  },
  {
    "id": 80,
    "statement": "Thalamus filters sensory info through neural oscillations and gating mechanisms."
  },
  {
    "id": 81,
    "statement": "GABA reduces neuron excitability through chloride ion influx."
  },
  {
    "id": 82,
    "statement": "Cultural practices shape emotional responses through socialization and norms"
  },
  {
    "id": 83,
    "statement": "Transparency builds trust through clear expectations, reducing uncertainty."
  },
  {
    "id": 84,
    "statement": "GABA's inhibitory action reduces neuron excitability through hyperpolarization."
  },
  {
    "id": 85,
    "statement": "Biological and cultural factors interact reciprocally in moral development models."
  },
  {
    "id": 86,
    "statement": "Emotional stability fosters consistent predictable behavior, building trust"
  },
  {
    "id": 87,
    "statement": "Moral development emerges from dynamic biological-cultural interplay."
  },
  {
    "id": 88,
    "statement": "Amygdala's hierarchical processing facilitates rapid emotional pattern recognition."
  },
  {
    "id": 89,
    "statement": "Consistency, reliability, and predictability build trust through interactive mechanisms."
  },
  {
    "id": 90,
    "statement": "GABA calms neurons by increasing chloride ion influx."
  },
  {
    "id": 91,
    "statement": "Hierarchical amygdala processing enables rapid emotional pattern recognition."
  },
  {
    "id": 92,
    "statement": "Consistency, reliability, and predictability combine to build trust cumulatively"
  },
  {
    "id": 93,
    "statement": "GABA calms neurons by increasing chloride ion influx hyperpolarizing them."
  },
  {
    "id": 94,
    "statement": "Consistency in performance refers to reliable delivery of promises."
  },
  {
    "id": 95,
    "statement": "Moral development arises from biological-cultural reciprocal interactions."
  },
  {
    "id": 96,
    "statement": "Amygdala rapidly processes emotional stimuli through efficient pathways"
  },
  {
    "id": 97,
    "statement": "Gamma oscillations enhance thalamus's selective sensory information processing"
  },
  {
    "id": 98,
    "statement": "Amygdala rapidly detects emotional significance in sensory information through hierarchy."
  },
  {
    "id": 99,
    "statement": "Amygdala processes emotional patterns through hierarchical neural interactions"
  },
  {
    "id": 100,
    "statement": "Amygdala pattern recognition is complex and dynamic process influenced."
  },
  {
    "id": 101,
    "statement": "Lying can be morally justifiable in context-dependent situations."
  },
  {
    "id": 102,
    "statement": "Emotional stability leads to consistent predictable emotive responses building trust"
  },
  {
    "id": 103,
    "statement": "The amygdala integrates sensory and emotional information rapidly."
  },
  {
    "id": 104,
    "statement": "GABA inhibitory action reduces neuron excitability through hyperpolarization."
  },
  {
    "id": 105,
    "statement": "Cultural norms shape emotional expressions and trust-building behaviors distinctly."
  },
  {
    "id": 106,
    "statement": "GABA binds to receptors, opening chloride channels to calm neurons."
  },
  {
    "id": 107,
    "statement": "The amygdala recognizes patterns through sensory, memory, and attention integration."
  },
  {
    "id": 108,
    "statement": "Hierarchical processing aids rapid emotion pattern recognition in amygdala"
  },
  {
    "id": 109,
    "statement": "Lying can be morally justifiable in context-dependent situations."
  },
  {
    "id": 110,
    "statement": "Gamma waves integrate sensory and emotional information through synchronization."
  },
  {
    "id": 111,
    "statement": "Amygdala quickly interprets sensory information for emotional significance."
  },
  {
    "id": 112,
    "statement": "Synaptic plasticity refines emotional responses in amygdala through neural adaptations"
  },
  {
    "id": 113,
    "statement": "Amygdala integrates sensory and emotional information rapidly, detecting patterns."
  },
  {
    "id": 114,
    "statement": "Trust arises from complex interplay of cognitive, emotional, and social processes."
  },
  {
    "id": 115,
    "statement": "Theory of mind and pattern recognition build trust through understanding."
  },
  {
    "id": 116,
    "statement": "Lying may be justifiable in situations of moral complexity."
  },
  {
    "id": 117,
    "statement": "GABA's inhibitory action reduces neuronal excitability through hyperpolarization"
  },
  {
    "id": 118,
    "statement": "Hierarchical processing enables amygdala to rapidly detect emotional patterns."
  },
  {
    "id": 119,
    "statement": "Emotional stability involves complex interplay of multiple factors."
  },
  {
    "id": 120,
    "statement": "Amygdala quickly assesses and responds to emotional stimuli rapidly"
  },
  {
    "id": 121,
    "statement": "Synaptic plasticity enables amygdala to refine emotional responses over time."
  },
  {
    "id": 122,
    "statement": "Amygdala's synaptic plasticity refines emotional responses through connection modification."
  },
  {
    "id": 123,
    "statement": "Thalamus filters sensory information through gamma frequency oscillations"
  },
  {
    "id": 124,
    "statement": "Cognitive factors influence trust building through pattern recognition."
  },
  {
    "id": 125,
    "statement": "Amygdala rapidly analyzes sensory information for emotional significance."
  },
  {
    "id": 126,
    "statement": "Hierarchical processing enables the amygdala to rapidly detect emotional patterns."
  },
  {
    "id": 127,
    "statement": "Amygdala emotional responses refined through experience-based synaptic plasticity"
  },
  {
    "id": 128,
    "statement": "Gamma waves facilitate brain region integration for emotional processing coherence."
  },
  {
    "id": 129,
    "statement": "Hierarchical processing facilitates rapid pattern recognition in amygdala outputs."
  },
  {
    "id": 130,
    "statement": "GABA reduces neuron excitability through chloride ion influx."
  },
  {
    "id": 131,
    "statement": "Contextual truthfulness prioritizes greater moral good over honesty."
  },
  {
    "id": 132,
    "statement": "GABA's inhibitory action reduces neuron excitability through hyperpolarization."
  },
  {
    "id": 133,
    "statement": "GABA calms neurons through both hyperpolarization and chloride influx."
  },
  {
    "id": 134,
    "statement": "Consistency, reliability, and predictability build trust through dependability."
  },
  {
    "id": 135,
    "statement": "Brain oscillations synchronize across regions for efficient information processing."
  },
  {
    "id": 136,
    "statement": "The amygdala processes emotions hierarchically from sensory information."
  },
  {
    "id": 137,
    "statement": "Hierarchical processing enables amygdala's rapid emotional pattern detection through efficient integration."
  },
  {
    "id": 138,
    "statement": "GABA's inhibitory action reduces neuron excitability through hyperpolarization."
  },
  {
    "id": 139,
    "statement": "Pattern recognition builds trust through consistent behavioral patterns recognition"
  },
  {
    "id": 140,
    "statement": "Thalamus filters sensory information through neural oscillations and gating mechanisms."
  },
  {
    "id": 141,
    "statement": "Transparency necessary but insufficient for building trustworthy relationships"
  },
  {
    "id": 142,
    "statement": "Consistency reliability dependability build trust through predictability stability"
  },
  {
    "id": 143,
    "statement": "Hierarchical amygdala processing enables rapid emotion pattern recognition through integration."
  },
  {
    "id": 144,
    "statement": "Emotional stability fosters predictability, consistency, and transparency in trust."
  },
  {
    "id": 145,
    "statement": "The amygdala recognizes patterns through sensory memory attention integration."
  },
  {
    "id": 146,
    "statement": "Delta oscillations regulate emotional responses in amygdala processing."
  },
  {
    "id": 147,
    "statement": "The amygdala processes emotions through hierarchical pattern recognition."
  },
  {
    "id": 148,
    "statement": "Moral development arises from complex biological-cultural interplay dynamics."
  },
  {
    "id": 149,
    "statement": "Transparency is necessary, but not sufficient, for building trust."
  },
  {
    "id": 150,
    "statement": "Moral development emerges from dynamic biological-cultural interactions."
  },
  {
    "id": 151,
    "statement": "Amygdala pattern recognition is complex, dynamic, and context-dependent process."
  },
  {
    "id": 152,
    "statement": "Honesty is crucial for trust, but not always sufficient."
  },
  {
    "id": 153,
    "statement": "Hierarchy in amygdala processing enables rapid emotional pattern detection."
  },
  {
    "id": 154,
    "statement": "Hierarchical processing in amygdala enables rapid emotional pattern recognition."
  },
  {
    "id": 155,
    "statement": "Synaptic plasticity updates refine emotional responses through neural connections"
  },
  {
    "id": 156,
    "statement": "Biological and cultural factors dynamically influence moral development."
  },
  {
    "id": 157,
    "statement": "Biological factors interact with environment and culture to shape moral development."
  },
  {
    "id": 158,
    "statement": "The amygdala rapidly detects emotions through hierarchical integration."
  },
  {
    "id": 159,
    "statement": "Trust construction involves multiple factors beyond honesty alone"
  },
  {
    "id": 160,
    "statement": "Amygdala integrates sensory and emotional information through hierarchical processing."
  },
  {
    "id": 161,
    "statement": "GABA inhibitory action reduces neuronal excitability through hyperpolarization."
  },
  {
    "id": 162,
    "statement": "Cultural socialization shapes emotional responses and regulation through learning."
  },
  {
    "id": 163,
    "statement": "Thalamus dynamically modulates sensory processing based on attentional state."
  },
  {
    "id": 164,
    "statement": "Transparency in trust building involves open communication, clarity, consistency, and accountability"
  },
  {
    "id": 165,
    "statement": "Amygdala refines emotional responses through synaptic plasticity adaptation."
  },
  {
    "id": 166,
    "statement": "Biological and cultural factors influence each other morally."
  },
  {
    "id": 167,
    "statement": "Emotional salience bidirectionally influences attention and neural oscillations dynamically."
  },
  {
    "id": 168,
    "statement": "Consistency, reliability, dependability, predictability, and stability build trust cumulatively."
  },
  {
    "id": 169,
    "statement": "Emotional stability enables consistent and predictable behavior through self-regulation."
  },
  {
    "id": 170,
    "statement": "Moral development emerges from dynamic biological-cultural interactions."
  },
  {
    "id": 171,
    "statement": "Emotional regulation enables individuals to exhibit consistent behavioral patterns"
  },
  {
    "id": 172,
    "statement": "Amygdala refines emotional responses through synaptic plasticity adaptation processing."
  },
  {
    "id": 173,
    "statement": "Lying can be morally justified in exceptional circumstances"
  },
  {
    "id": 174,
    "statement": "Emotional stability builds on self-regulation, enabling consistent behavior."
  },
  {
    "id": 175,
    "statement": "Biological and cultural factors interact reciprocally in moral development"
  },
  {
    "id": 176,
    "statement": "Thalamus acts as a sensory gatekeeper for focused attention."
  },
  {
    "id": 177,
    "statement": "GABA binds to receptors, opening chloride channels to calm neurons."
  },
  {
    "id": 178,
    "statement": "Cultural norms influence emotional expressions and regulation through socialization."
  },
  {
    "id": 179,
    "statement": "Thalamus filters sensory info through neural oscillations and gating mechanisms."
  },
  {
    "id": 180,
    "statement": "Honesty at foundation of trust through consistent truthfulness."
  },
  {
    "id": 181,
    "statement": "Amygdala's emotional responses refined through synaptic plasticity adaptation."
  },
  {
    "id": 182,
    "statement": "Synaptic plasticity refines emotional responses through amygdala adaptation."
  },
  {
    "id": 183,
    "statement": "Moral development emerges from interplay between biology and culture."
  },
  {
    "id": 184,
    "statement": "Hierarchical amygdala processing enables rapid emotional pattern detection."
  },
  {
    "id": 185,
    "statement": "Thalamus modulates sensory information gating through neural oscillations."
  },
  {
    "id": 186,
    "statement": "Cognitive factors, particularly pattern recognition, build trust through interpretation in individuals."
  },
  {
    "id": 187,
    "statement": "Amygdala's pattern recognition shaped by internal and external factors interaction."
  },
  {
    "id": 188,
    "statement": "Trust emerges from dynamic interactions of cognition, emotion, and society."
  },
  {
    "id": 189,
    "statement": "Amygdala rapidly analyzes multiple sensory inputs in parallel."
  },
  {
    "id": 190,
    "statement": "Moral development arises from dynamic biology-culture interaction"
  },
  {
    "id": 191,
    "statement": "The amygdala integrates sensory and motor information for emotional recognition."
  },
  {
    "id": 192,
    "statement": "Familiarity fosters trust through cognitive and emotional pattern recognition"
  },
  {
    "id": 193,
    "statement": "Amygdala recognizes patterns in sensory info through hierarchical processing."
  },
  {
    "id": 194,
    "statement": "Genetics, experience, and culture interactively shape amygdala pattern recognition"
  },
  {
    "id": 195,
    "statement": "Hierarchical processing enables amygdala to rapidly integrate emotional information."
  },
  {
    "id": 196,
    "statement": "Consistency, reliability, and predictability build trust cumulatively through interdependence."
  },
  {
    "id": 197,
    "statement": "Theory of Mind recognizes patterns in others' behavior through understanding."
  },
  {
    "id": 198,
    "statement": "GABA's inhibitory action hyperpolarizes neurons by allowing chloride ions"
  },
  {
    "id": 199,
    "statement": "Cultural norms influence emotional expressions and trust-building behaviors complexly"
  }
]